{
  "content": [
    {
      "id": "qfglcc",
      "name": "section",
      "parent": 0,
      "children": [
        "mqqoyv"
      ],
      "settings": {
        "_cssGlobalClasses": [
          "irwjno"
        ]
      },
      "label": "Content"
    },
    {
      "id": "mqqoyv",
      "name": "container",
      "parent": "qfglcc",
      "children": [
        "wzkcci",
        "canglq",
        "iklcvq"
      ],
      "settings": {
        "_cssGlobalClasses": [
          "fvdqst"
        ]
      }
    },
    {
      "id": "ggjagk",
      "name": "block",
      "parent": "wzkcci",
      "children": [
        "zpywqc",
        "frnjbq"
      ],
      "settings": {
        "_cssGlobalClasses": [
          "bybvsc"
        ]
      },
      "label": "Inner container info"
    },
    {
      "id": "zpywqc",
      "name": "text-basic",
      "parent": "ggjagk",
      "children": [],
      "settings": {
        "text": "Tagline",
        "tag": "p",
        "_cssGlobalClasses": [
          "triban"
        ]
      },
      "label": "Tagline"
    },
    {
      "id": "frnjbq",
      "name": "heading",
      "parent": "ggjagk",
      "children": [],
      "settings": {
        "text": "Ut tempus dui non enim<br>accumsan, eu rutrum turpis<br>",
        "_cssGlobalClasses": [
          "hsyrog"
        ],
        "tag": "h2"
      }
    },
    {
      "id": "hbripe",
      "name": "image",
      "parent": "iklcvq",
      "children": [],
      "settings": {
        "_cssGlobalClasses": [
          "wgvsni"
        ],
        "image": {
          "url": "https://acss.brixies.co/wp-content/uploads/2023/10/placeholder-image-4-3-xxl.png",
          "external": true,
          "filename": "placeholder-image-4-3-xxl.png"
        },
        "tag": "figure"
      },
      "themeStyles": []
    },
    {
      "id": "canglq",
      "name": "text",
      "parent": "mqqoyv",
      "children": [],
      "settings": {
        "text": "<p>Lorem ipsum dolor sit amet consectetur adipiscing elit lectus dapibus natoque viverra in lectus mauris est elementum in lectus curabitur vivamus sit eget adipiscing pellentesque neque montes sit malesuada cum diam et vivamus congue fermentum dui imperdiet cursus velit hendrerit elit leo proin nec dignissim urna aenean.</p><p>Lorem ipsum dolor sit amet consectetur adipiscing elit lectus dapibus natoque viverra in lectus mauris est elementum in lectus curabitur vivamus sit eget adipiscing pellentesque neque montes sit malesuada cum diam et vivamus congue fermentum dui imperdiet cursus velit hendrerit elit leo proin nec dignissim urna aenean.</p>",
        "_cssGlobalClasses": [
          "blzxpv"
        ]
      },
      "label": "Description"
    },
    {
      "id": "hxilpz",
      "name": "code",
      "parent": 0,
      "children": [],
      "settings": {
        "executeCode": true,
        "signature": "224ab13de7558d42c38e05c804f83ddd",
        "user_id": 2,
        "time": 1720984823,
        "cssCode": "/* -- The root styles must go in the element of the structure with the name \"Description\". --*/\n\n/* Styles that will make the description distribute into two columns evenly.\n\n- The \"column-gap\" property is used to provide spacing between the two columns.\n*/\n.content-28__description{\n  column-count:2;\n  column-gap: var(--space-m);\n\n  /* Styles for tablet version */\n  @media(max-width: 991px){\n    column-gap:var(--space-s);\n  }\n\n  /* Styles for the mobile version */\n  @media(max-width: 767px){\n    column-count:1;\n  }\n}"
      },
      "label": "Styles CSS",
      "themeStyles": []
    },
    {
      "id": "wzkcci",
      "name": "block",
      "parent": "mqqoyv",
      "children": [
        "ggjagk",
        "qkqmrv"
      ],
      "settings": {
        "_cssGlobalClasses": [
          "anqvaq"
        ]
      },
      "label": "Container info"
    },
    {
      "id": "qkqmrv",
      "name": "button",
      "parent": "wzkcci",
      "children": [],
      "settings": {
        "text": "Contact now",
        "style": "dark",
        "_cssGlobalClasses": [
          "blgqti"
        ],
        "link": {
          "type": "external",
          "url": "#"
        }
      }
    },
    {
      "id": "iklcvq",
      "name": "block",
      "parent": "mqqoyv",
      "children": [
        "hbripe",
        "nhxktc"
      ],
      "settings": {
        "_cssGlobalClasses": [
          "wxcsxy"
        ]
      },
      "label": "Images"
    },
    {
      "id": "nhxktc",
      "name": "image",
      "parent": "iklcvq",
      "children": [],
      "settings": {
        "_cssGlobalClasses": [
          "wgvsni"
        ],
        "image": {
          "url": "https://acss.brixies.co/wp-content/uploads/2023/10/placeholder-image-4-3-xxl.png",
          "external": true,
          "filename": "placeholder-image-4-3-xxl.png"
        },
        "tag": "figure"
      },
      "themeStyles": []
    }
  ],
  "source": "bricksCopiedElements",
  "sourceUrl": "https://cf.brixies.co",
  "version": "1.11",
  "globalClasses": [
    {
      "id": "irwjno",
      "name": "content-28",
      "settings": {
        "_background": {
          "color": {
            "raw": "var(--light)",
            "id": "01H7XJZ0KTXZ00FKVG3Y345XCP",
            "name": "light"
          }
        },
        "_overflow": "hidden"
      }
    },
    {
      "id": "fvdqst",
      "name": "content-28__container",
      "settings": {
        "_rowGap": "var(--space-l)"
      }
    },
    {
      "id": "bybvsc",
      "name": "content-28__inner-container-info",
      "settings": {
        "_rowGap": "var(--space-xs)"
      }
    },
    {
      "id": "triban",
      "name": "content-28__tagline",
      "settings": {
        "_margin": {
          "bottom": "0"
        },
        "_typography": {
          "font-weight": "600",
          "color": {
            "raw": "var(--dark)",
            "id": "01H7XJZ4GBR5DD6Q0547QE5P4H",
            "name": "dark"
          }
        }
      }
    },
    {
      "id": "hsyrog",
      "name": "content-28__heading",
      "settings": {
        "_typography": {
          "font-size": "var(--text-2xl)"
        },
        "_margin": {
          "top": "0"
        },
        "_width": "810"
      }
    },
    {
      "id": "wgvsni",
      "name": "content-28__img",
      "settings": {
        "_aspectRatio": "4 / 3",
        "_objectFit": "cover",
        "_objectPosition": "50%",
        "_flexShrink": "0",
        "_width": "66%",
        "_width:mobile_landscape": "100%"
      }
    },
    {
      "id": "blzxpv",
      "name": "content-28__description",
      "settings": []
    },
    {
      "id": "anqvaq",
      "name": "content-28__container-info",
      "settings": {
        "_direction": "row",
        "_alignItems": "flex-end",
        "_rowGap": "var(--space-l)",
        "_columnGap": "var(--space-m)"
      }
    },
    {
      "id": "blgqti",
      "name": "content-28__btn",
      "settings": {
        "_flexShrink": "0",
        "_margin": {
          "top": "0"
        }
      }
    },
    {
      "id": "wxcsxy",
      "name": "content-28__container-img",
      "settings": {
        "_flexWrap": "nowrap",
        "_direction": "row",
        "_columnGap": "var(--space-m)",
        "_columnGap:tablet_portrait": "var(--space-s)",
        "_direction:mobile_landscape": "column",
        "_rowGap:mobile_landscape": "var(--space-s)"
      }
    }
  ],
  "globalElements": []
}