{
  "content": [
    {
      "id": "yczhix",
      "name": "section",
      "parent": 0,
      "children": [
        "iyrgsw"
      ],
      "settings": {
        "_cssGlobalClasses": [
          "ajolcn"
        ]
      },
      "label": "CTA"
    },
    {
      "id": "iyrgsw",
      "name": "container",
      "parent": "yczhix",
      "children": [
        "zgcmyl",
        "dcuclw",
        "pjevpw",
        "xxniar"
      ],
      "settings": {
        "_cssGlobalClasses": [
          "lxltcy"
        ]
      }
    },
    {
      "id": "zgcmyl",
      "name": "image",
      "parent": "iyrgsw",
      "children": [],
      "settings": {
        "tag": "figure",
        "_cssGlobalClasses": [
          "zofjoc"
        ],
        "image": {
          "url": "https://acss.brixies.co/wp-content/uploads/2024/06/Img-placeholder-16-9.png",
          "external": true,
          "filename": "Img-placeholder-16-9.png"
        }
      },
      "themeStyles": {},
      "label": "Background image"
    },
    {
      "id": "dcuclw",
      "name": "div",
      "parent": "iyrgsw",
      "children": [],
      "settings": {
        "_cssGlobalClasses": [
          "ymmpxl"
        ]
      },
      "label": "Overlay"
    },
    {
      "id": "zkhiec",
      "name": "text-basic",
      "parent": "fkzhtx",
      "children": [],
      "settings": {
        "text": "Tagline",
        "tag": "p",
        "_cssGlobalClasses": [
          "trthms"
        ]
      },
      "label": "Tagline"
    },
    {
      "id": "qohzct",
      "name": "heading",
      "parent": "fkzhtx",
      "children": [],
      "settings": {
        "text": "Lorem ipsum dolor sit amet ",
        "_cssGlobalClasses": [
          "ealcoj"
        ],
        "tag": "h2"
      }
    },
    {
      "id": "voszbg",
      "name": "text-basic",
      "parent": "fkzhtx",
      "children": [],
      "settings": {
        "text": "Lorem ipsum dolor sit amet, consectetur adipiscing elit, sed do eiusmod tempor incididunt ut labore et dolore.",
        "tag": "p",
        "_cssGlobalClasses": [
          "xpjxxy"
        ]
      },
      "label": "Description"
    },
    {
      "id": "doerxx",
      "name": "block",
      "parent": "pjevpw",
      "children": [
        "amhrzx",
        "cniusq"
      ],
      "settings": {
        "_cssGlobalClasses": [
          "nsxmcl"
        ]
      },
      "label": "Container button"
    },
    {
      "id": "amhrzx",
      "name": "button",
      "parent": "doerxx",
      "children": [],
      "settings": {
        "text": "Contact now",
        "_cssGlobalClasses": [
          "vwllyg"
        ],
        "link": {
          "type": "external",
          "url": "#"
        },
        "style": "light"
      }
    },
    {
      "id": "cniusq",
      "name": "button",
      "parent": "doerxx",
      "children": [],
      "settings": {
        "text": "See more",
        "_cssGlobalClasses": [
          "ndfjjf"
        ],
        "link": {
          "type": "external",
          "url": "#"
        },
        "outline": true,
        "style": "dark"
      },
      "label": "Button outline"
    },
    {
      "id": "pjevpw",
      "name": "block",
      "parent": "iyrgsw",
      "children": [
        "fkzhtx",
        "doerxx"
      ],
      "settings": {
        "_cssGlobalClasses": [
          "xbiocx"
        ]
      },
      "label": "Container info"
    },
    {
      "id": "xxniar",
      "name": "image",
      "parent": "iyrgsw",
      "children": [],
      "settings": {
        "tag": "figure",
        "image": {
          "url": "https://acss.brixies.co/wp-content/uploads/2023/10/Img-placeholder-16-9.png",
          "external": true,
          "filename": "Img-placeholder-16-9.png"
        },
        "_cssGlobalClasses": [
          "htudfe"
        ]
      },
      "themeStyles": {}
    },
    {
      "id": "fkzhtx",
      "name": "block",
      "parent": "pjevpw",
      "children": [
        "zkhiec",
        "qohzct",
        "voszbg"
      ],
      "settings": {
        "_cssGlobalClasses": [
          "jolefm"
        ]
      },
      "label": "Inner container info"
    }
  ],
  "source": "bricksCopiedElements",
  "sourceUrl": "https://cf.brixies.co",
  "version": "1.9.9",
  "globalClasses": [
    {
      "id": "ajolcn",
      "name": "cta-29",
      "settings": {}
    },
    {
      "id": "lxltcy",
      "name": "cta-29__container",
      "settings": {
        "_position": "relative",
        "_overflow": "hidden",
        "_isolation": "isolate",
        "_direction": "column",
        "_rowGap": "var(--space-xl)",
        "_alignItems": "center",
        "_padding": {
          "top": "var(--space-xl)",
          "right": "var(--space-xl)",
          "bottom": "0",
          "left": "var(--space-xl)"
        },
        "_border": {
          "radius": {
            "top": "var(--radius-m)",
            "right": "var(--radius-m)",
            "bottom": "var(--radius-m)",
            "left": "var(--radius-m)"
          }
        },
        "_padding:mobile_portrait": {
          "top": "var(--space-xl)",
          "right": "var(--space-m)",
          "bottom": "var(--space-m)",
          "left": "var(--space-m)"
        }
      }
    },
    {
      "id": "zofjoc",
      "name": "cta-29__bg-img",
      "settings": {
        "_objectFit": "cover",
        "_objectPosition": "50%",
        "_width": "100%",
        "_height": "100%",
        "_position": "absolute",
        "_zIndex": "-1",
        "_top": "0",
        "_right": "0"
      }
    },
    {
      "id": "ymmpxl",
      "name": "cta-29__overlay",
      "settings": {
        "_width": "100%",
        "_height": "100%",
        "_position": "absolute",
        "_zIndex": "-1",
        "_background": {
          "color": {
            "raw": "var(--dark-50)",
            "id": "01H7XJZ4GBR5DD6Q0547QE5P4H.50",
            "name": "dark-50"
          }
        },
        "_top": "0",
        "_right": "0"
      }
    },
    {
      "id": "trthms",
      "name": "cta-29__tagline",
      "settings": {
        "_typography": {
          "color": {
            "raw": "var(--light)",
            "id": "01H7XJZ0KTXZ00FKVG3Y345XCP",
            "name": "light"
          },
          "font-weight": "600",
          "text-align": "center"
        },
        "_margin": {
          "bottom": "0"
        }
      }
    },
    {
      "id": "ealcoj",
      "name": "cta-29__heading",
      "settings": {
        "_typography": {
          "color": {
            "raw": "var(--light)",
            "id": "01H7XJZ0KTXZ00FKVG3Y345XCP",
            "name": "light"
          },
          "text-align": "center",
          "font-size": "var(--text-2xl)"
        }
      },
      "modified": 1719197874,
      "user_id": 2
    },
    {
      "id": "xpjxxy",
      "name": "cta-29__description",
      "settings": {
        "_typography": {
          "color": {
            "raw": "var(--light-80)",
            "id": "01H7XJZ0KTXZ00FKVG3Y345XCP.80",
            "name": "light-80"
          },
          "text-align": "center"
        },
        "_widthMax": "540"
      }
    },
    {
      "id": "nsxmcl",
      "name": "cta-29__container-btn",
      "settings": {
        "_width": "auto",
        "_direction": "row",
        "_flexWrap": "nowrap",
        "_columnGap": "var(--space-s)",
        "_alignItems": "stretch",
        "_direction:mobile_portrait": "column",
        "_rowGap": "var(--space-s)",
        "_width:mobile_portrait": "100%"
      }
    },
    {
      "id": "vwllyg",
      "name": "cta-29__btn",
      "settings": {}
    },
    {
      "id": "ndfjjf",
      "name": "cta-29__btn-outline",
      "settings": {}
    },
    {
      "id": "xbiocx",
      "name": "cta-29__container-info",
      "settings": {
        "_direction": "column",
        "_alignItems": "center",
        "_rowGap": "var(--space-l)",
        "_widthMax": "810"
      }
    },
    {
      "id": "htudfe",
      "name": "cta-29__img",
      "settings": {
        "_aspectRatio": "2 / 1",
        "_objectFit": "cover",
        "_objectPosition": "50%",
        "_border": {
          "radius": {
            "top": "var(--radius-s)",
            "right": "var(--radius-s)"
          }
        },
        "_border:mobile_portrait": {
          "radius": {
            "top": "var(--radius-s)",
            "right": "var(--radius-s)",
            "bottom": "var(--radius-s)",
            "left": "var(--radius-s)"
          }
        }
      }
    },
    {
      "id": "jolefm",
      "name": "cta-29__inner-container-info",
      "settings": {
        "_alignItems": "center",
        "_rowGap": "var(--space-xs)",
        "_margin:mobile_portrait": {
          "top": "0"
        }
      }
    }
  ],
  "globalElements": []
}