{
  "content": [
    {
      "id": "nbynhn",
      "name": "section",
      "parent": 0,
      "children": [
        "romztc",
        "yxwufp"
      ],
      "settings": {
        "_cssGlobalClasses": [
          "pqmlln"
        ]
      },
      "label": "FAQ"
    },
    {
      "id": "romztc",
      "name": "container",
      "parent": "nbynhn",
      "children": [
        "nernls",
        "hggeol"
      ],
      "settings": {
        "_cssGlobalClasses": [
          "extgus"
        ]
      }
    },
    {
      "id": "nernls",
      "name": "block",
      "parent": "romztc",
      "children": [
        "pspsyp",
        "wpwrpw",
        "dzdvio"
      ],
      "settings": {
        "_cssGlobalClasses": [
          "hocxgr"
        ]
      },
      "label": "Container info"
    },
    {
      "id": "pspsyp",
      "name": "heading",
      "parent": "nernls",
      "children": [],
      "settings": {
        "text": "Frequently Asked Questions",
        "_cssGlobalClasses": [
          "iwrrqf"
        ],
        "tag": "h2"
      }
    },
    {
      "id": "wpwrpw",
      "name": "text",
      "parent": "nernls",
      "children": [],
      "settings": {
        "text": "<p>At vero eos et accusamus et iusto odio dignissimos ducimus qui blanditiis praesentium voluptatum deleniti atque corrupti.</p>",
        "_cssGlobalClasses": [
          "iykzfy"
        ]
      },
      "label": "Description"
    },
    {
      "id": "dzdvio",
      "name": "button",
      "parent": "nernls",
      "children": [],
      "settings": {
        "text": "Contact",
        "_cssGlobalClasses": [
          "khbddp"
        ],
        "link": {
          "type": "external",
          "url": "#"
        },
        "style": "dark"
      }
    },
    {
      "id": "hggeol",
      "name": "block",
      "parent": "romztc",
      "children": [
        "yaeuna"
      ],
      "settings": {
        "_cssGlobalClasses": [
          "vklhlf"
        ],
        "tag": "div"
      },
      "label": "Container faq"
    },
    {
      "id": "yaeuna",
      "name": "accordion-nested",
      "parent": "hggeol",
      "children": [
        "afezbx"
      ],
      "settings": {
        "_cssGlobalClasses": [
          "qwlcuc"
        ],
        "_attributes": [
          {
            "id": "nqtjdu",
            "name": "itemscope"
          },
          {
            "id": "dwxdba",
            "name": "itemtype",
            "value": "https://schema.org/FAQPage"
          },
          {
            "id": "xbjmpy",
            "name": "role",
            "value": "list"
          }
        ]
      },
      "label": "Accordion",
      "themeStyles": []
    },
    {
      "id": "afezbx",
      "name": "block",
      "parent": "yaeuna",
      "children": [
        "webozq",
        "udkdqp"
      ],
      "settings": {
        "_cssGlobalClasses": [
          "lspjzm"
        ],
        "_attributes": [
          {
            "id": "nemrnb",
            "name": "itemscope"
          },
          {
            "id": "gpnemq",
            "name": "itemprop",
            "value": "mainEntity"
          },
          {
            "id": "iqoswa",
            "name": "itemtype",
            "value": "https://schema.org/Question"
          },
          {
            "id": "rpzfna",
            "name": "role",
            "value": "listitem"
          }
        ],
        "query": {
          "posts_per_page": "5"
        }
      },
      "label": "Item"
    },
    {
      "id": "webozq",
      "name": "block",
      "parent": "afezbx",
      "children": [
        "tbwxmp",
        "okiogz"
      ],
      "settings": {
        "_hidden": {
          "_cssClasses": "accordion-title-wrapper"
        },
        "_cssGlobalClasses": [
          "ikacne"
        ],
        "tag": "custom",
        "customTag": "button",
        "_attributes": [
          {
            "id": "uqvqjx",
            "name": "aria-expanded",
            "value": "false"
          },
          {
            "id": "glintd",
            "name": "role",
            "value": "button"
          }
        ]
      },
      "label": "Title"
    },
    {
      "id": "tbwxmp",
      "name": "heading",
      "parent": "webozq",
      "children": [],
      "settings": {
        "text": "Lorem ipsum dolor",
        "tag": "h3",
        "_cssGlobalClasses": [
          "bzofma"
        ],
        "_attributes": [
          {
            "id": "yxsaxo",
            "name": "itemprop",
            "value": "name"
          }
        ]
      },
      "label": "Question"
    },
    {
      "id": "okiogz",
      "name": "icon",
      "parent": "webozq",
      "children": [],
      "settings": {
        "icon": {
          "library": "fontawesomeSolid",
          "icon": "fas fa-plus"
        },
        "_cssGlobalClasses": [
          "bccnuf"
        ]
      },
      "themeStyles": []
    },
    {
      "id": "udkdqp",
      "name": "block",
      "parent": "afezbx",
      "children": [
        "ngngxs"
      ],
      "settings": {
        "_hidden": {
          "_cssClasses": "accordion-content-wrapper"
        },
        "_cssGlobalClasses": [
          "omaezq"
        ],
        "_attributes": [
          {
            "id": "kncpjo",
            "name": "itemscope"
          },
          {
            "id": "jcbadj",
            "name": "itemprop",
            "value": "acceptedAnswer"
          },
          {
            "id": "xajeoj",
            "name": "itemtype",
            "value": "https://schema.org/Answer"
          }
        ]
      },
      "label": "Content"
    },
    {
      "id": "ngngxs",
      "name": "text",
      "parent": "udkdqp",
      "children": [],
      "settings": {
        "text": "<p>Lorem ipsum dolor sit amet consectetur. Velit orci mi tristique tincidunt at ipsum. Vitae vestibulum amet suspendisse amet vitae natoque sem feugiat sed. Facilisis enim donec amet sit mi duis massa at. Sit adipiscing varius viverra malesuada orci arcu nunc sit viverra. Nulla curabitur felis sagittis euismod.</p>",
        "_cssGlobalClasses": [
          "yrhlkw"
        ],
        "_attributes": [
          {
            "id": "jacowd",
            "name": "itemprop",
            "value": "text"
          }
        ]
      },
      "label": "Answer"
    },
    {
      "id": "yxwufp",
      "name": "code",
      "parent": "nbynhn",
      "children": [],
      "settings": {
        "executeCode": true,
        "signature": "0cc67fc3bef079081441f2e97084b95d",
        "user_id": 2,
        "time": 1720984823,
        "javascriptCode": "/* The purpose of the script is to have the aria-expanded and aria-controls attributes for web accessibility. \n You can remove this script and the accordion will still work. */\nconst btnFaq = document.querySelectorAll('.faq-5__question');\nconst contentFaq = document.querySelectorAll('.faq-5__answer');\n\nbtnFaq.forEach((button) => {\n  button.addEventListener('click', () => {\n    // Gets the current state of the button\n    const isExpanded = button.getAttribute('aria-expanded') === 'true';\n\n    // Reset all buttons to \"false\".\n    btnFaq.forEach((currentBtn) => {\n      currentBtn.setAttribute('aria-expanded', 'false');\n    });\n\n    // Changes the status of the current button\n    button.setAttribute('aria-expanded', isExpanded ? 'false' : 'true');\n  });\n});\n\n// Load function after HTML content is loaded\ndocument.addEventListener('DOMContentLoaded', function () {\n  // Make a tour on each button there is\n  btnFaq.forEach((button, i) => {\n    // Verify if the content exists before assigning aria-controls\n    const contentElement = contentFaq[i];\n\n    if (contentElement) {\n      const contentId = contentElement.getAttribute('id') || `faq-content-${i}`;\n      contentElement.setAttribute('id', contentId);\n      button.setAttribute('aria-controls', contentId);\n    } else {\n      // Set aria-controls to \"false\" if no content is available\n      button.setAttribute('aria-controls', 'false');\n    }\n  });\n});"
      },
      "label": "JS Accordion accesibility"
    }
  ],
  "source": "bricksCopiedElements",
  "sourceUrl": "https://cf.brixies.co",
  "version": "1.11.1.1",
  "globalClasses": [
    {
      "id": "pqmlln",
      "name": "faq-5",
      "settings": [],
      "modified": 1729014184,
      "user_id": 2
    },
    {
      "id": "extgus",
      "name": "faq-5__container",
      "settings": {
        "_direction:mobile_landscape": "column",
        "_rowGap:mobile_landscape": "var(--space-xl)",
        "_direction:tablet_portrait": "column",
        "_rowGap:tablet_portrait": "var(--space-xl)",
        "_display": "grid",
        "_gridGap": "var(--space-m)",
        "_gridTemplateColumns": "repeat(2, minmax(0, 1fr))",
        "_gridGap:tablet_portrait": "var(--space-xl)",
        "_gridTemplateColumns:tablet_portrait": "repeat(1, minmax(0, 1fr))"
      },
      "modified": 1723331667,
      "user_id": 2
    },
    {
      "id": "hocxgr",
      "name": "faq-5__container-info",
      "settings": {
        "_width": "545",
        "_widthMax": "100%",
        "_width:tablet_portrait": "100%"
      }
    },
    {
      "id": "iwrrqf",
      "name": "faq-5__heading",
      "settings": {
        "_typography": {
          "font-size": "var(--text-xl)"
        }
      }
    },
    {
      "id": "iykzfy",
      "name": "faq-5__description",
      "settings": {
        "_typography": {
          "font-size": "var(--text-m)"
        },
        "_margin": {
          "top": "var(--space-xs)"
        }
      }
    },
    {
      "id": "khbddp",
      "name": "faq-5__btn",
      "settings": {
        "_padding:mobile_portrait": {
          "bottom": "var(--space-s)",
          "top": "var(--space-s)"
        },
        "_margin": {
          "top": "var(--space-m)"
        }
      }
    },
    {
      "id": "vklhlf",
      "name": "faq-5__container-faq",
      "settings": {
        "_direction": "column",
        "_rowGap": "var(--space-l)",
        "_width:tablet_portrait": "100%",
        "_margin": {
          "top": "0",
          "bottom": "0"
        },
        "_padding": {
          "left": "0"
        }
      }
    },
    {
      "id": "qwlcuc",
      "name": "faq-5__accordion",
      "settings": {
        "titlePadding": {
          "top": "var(--space-m)",
          "bottom": "var(--space-m)"
        },
        "contentPadding": {
          "right": "0",
          "bottom": "var(--space-m)",
          "left": "0"
        },
        "_display": "flex",
        "_flexDirection": "column",
        "contentTypography": {
          "font-size": "var(--text-m)"
        },
        "titleBorder": {
          "width": {
            "top": "1"
          },
          "style": "solid",
          "color": {
            "raw": "var(--dark)",
            "id": "01H7XJZ4GBR5DD6Q0547QE5P4H",
            "name": "dark"
          }
        },
        "_border": {
          "width": {
            "bottom": "1"
          },
          "style": "solid",
          "color": {
            "raw": "var(--dark)",
            "id": "01H7XJZ4GBR5DD6Q0547QE5P4H",
            "name": "dark"
          }
        },
        "titleTypography": {
          "font-size": "var(--text-m)"
        }
      }
    },
    {
      "id": "lspjzm",
      "name": "faq-5__item",
      "settings": {},
      "modified": 1729014800,
      "user_id": 2
    },
    {
      "id": "ikacne",
      "name": "faq-5__question",
      "settings": {
        "_direction": "row",
        "_flexWrap": "nowrap",
        "_justifyContent": "space-between",
        "_alignItems": "center",
        "_background": {
          "color": {
            "raw": "transparent"
          }
        }
      }
    },
    {
      "id": "bzofma",
      "name": "faq-5__answer-heading",
      "settings": []
    },
    {
      "id": "bccnuf",
      "name": "faq-5__answer-icon",
      "settings": {
        "iconSize": "var(--text-l)",
        "_cssCustom": ".brx-open .faq-5__answer-icon{\n transform: rotate(45deg);\n}",
        "_cssTransition": "all .2s ease"
      }
    },
    {
      "id": "omaezq",
      "name": "faq-5__answer",
      "settings": []
    },
    {
      "id": "yrhlkw",
      "name": "faq-5__answer-content",
      "settings": []
    }
  ],
  "globalElements": []
}