{
  "content": [
    {
      "id": "atljzi",
      "name": "section",
      "parent": 0,
      "children": [
        "bcyeyq",
        "frrbdn",
        "hpvfhm"
      ],
      "settings": {
        "_cssGlobalClasses": [
          "qmfqfu"
        ]
      },
      "label": "Features"
    },
    {
      "id": "hpvfhm",
      "name": "code",
      "parent": "atljzi",
      "children": [],
      "settings": {
        "executeCode": true,
        "signature": "e7229027c0d067e8c3a29798caf79688",
        "user_id": 2,
        "time": 1721769648,
        "cssCode": "/* -- The root styles must go in the element of the structure with the name \"Card\". --*/\n.card-feature-61__wrapper {\n  counter-increment: item;\n\n  /* Styles and configuration of the outgoing card counter */\n  .card-feature-61:before {\n    /* You can remove the text “decimal-leading-zero” if you do not want the number to have a leading zero. */\n    content: counter(item, decimal-leading-zero);\n    font-size: var(--text-2xl);\n    font-weight: 700;\n    line-height: 1.2;\n    color: var(--dark);\n  }\n}"
      },
      "label": "CSS Styles",
      "themeStyles": []
    },
    {
      "id": "sdeqcm",
      "name": "block",
      "parent": "frrbdn",
      "children": [
        "kwkvlz",
        "puegxu",
        "tbbgmu"
      ],
      "settings": {
        "_cssGlobalClasses": [
          "axqpwz"
        ],
        "tag": "ul",
        "customTag": "li"
      },
      "label": "Grid"
    },
    {
      "id": "kwkvlz",
      "name": "block",
      "parent": "sdeqcm",
      "children": [
        "acmsgt"
      ],
      "settings": {
        "query": {
          "posts_per_page": "6"
        },
        "tag": "li",
        "_cssGlobalClasses": [
          "bvywvo"
        ]
      },
      "label": "Card wrapper"
    },
    {
      "id": "acmsgt",
      "name": "block",
      "parent": "kwkvlz",
      "children": [
        "glxbad",
        "mmqyvq"
      ],
      "settings": {
        "_cssGlobalClasses": [
          "uihqhz"
        ],
        "query": {
          "posts_per_page": "6"
        },
        "tag": "article"
      },
      "label": "Card"
    },
    {
      "id": "glxbad",
      "name": "block",
      "parent": "acmsgt",
      "children": [
        "hdbkqb",
        "scfnok"
      ],
      "settings": {
        "_cssGlobalClasses": [
          "bzdwqo"
        ]
      },
      "label": "Container info"
    },
    {
      "id": "hdbkqb",
      "name": "heading",
      "parent": "glxbad",
      "children": [],
      "settings": {
        "text": "Lorem ipsum",
        "_cssGlobalClasses": [
          "ykpeax"
        ],
        "tag": "h3"
      }
    },
    {
      "id": "scfnok",
      "name": "text",
      "parent": "glxbad",
      "children": [],
      "settings": {
        "text": "<p>Eos laudantium repellat sed architecto earum unde incidunt. Illum sit dolores voluptatem.</p>",
        "_cssGlobalClasses": [
          "ddiafu"
        ]
      },
      "label": "Description"
    },
    {
      "id": "mmqyvq",
      "name": "button",
      "parent": "acmsgt",
      "children": [],
      "settings": {
        "text": "Learn more",
        "_cssGlobalClasses": [
          "vkkdks"
        ],
        "link": {
          "type": "external",
          "url": "#"
        },
        "icon": {
          "library": "fontawesomeSolid",
          "icon": "fas fa-arrow-right"
        },
        "style": "dark"
      }
    },
    {
      "id": "puegxu",
      "name": "block",
      "parent": "sdeqcm",
      "children": [
        "cjplrr"
      ],
      "settings": {
        "query": {
          "posts_per_page": "6"
        },
        "tag": "li",
        "_cssGlobalClasses": [
          "bvywvo"
        ]
      },
      "label": "Card wrapper"
    },
    {
      "id": "cjplrr",
      "name": "block",
      "parent": "puegxu",
      "children": [
        "emydhi",
        "nwadqp"
      ],
      "settings": {
        "_cssGlobalClasses": [
          "uihqhz"
        ],
        "query": {
          "posts_per_page": "6"
        },
        "tag": "article"
      },
      "label": "Card"
    },
    {
      "id": "emydhi",
      "name": "block",
      "parent": "cjplrr",
      "children": [
        "galpmw",
        "pudaqr"
      ],
      "settings": {
        "_cssGlobalClasses": [
          "bzdwqo"
        ]
      },
      "label": "Container info"
    },
    {
      "id": "galpmw",
      "name": "heading",
      "parent": "emydhi",
      "children": [],
      "settings": {
        "text": "Lorem ipsum",
        "_cssGlobalClasses": [
          "ykpeax"
        ],
        "tag": "h3"
      }
    },
    {
      "id": "pudaqr",
      "name": "text",
      "parent": "emydhi",
      "children": [],
      "settings": {
        "text": "<p>Eos laudantium repellat sed architecto earum unde incidunt. Illum sit dolores voluptatem.</p>",
        "_cssGlobalClasses": [
          "ddiafu"
        ]
      },
      "label": "Description"
    },
    {
      "id": "nwadqp",
      "name": "button",
      "parent": "cjplrr",
      "children": [],
      "settings": {
        "text": "Learn more",
        "_cssGlobalClasses": [
          "vkkdks"
        ],
        "link": {
          "type": "external",
          "url": "#"
        },
        "icon": {
          "library": "fontawesomeSolid",
          "icon": "fas fa-arrow-right"
        },
        "style": "dark"
      }
    },
    {
      "id": "tbbgmu",
      "name": "block",
      "parent": "sdeqcm",
      "children": [
        "lgytwl"
      ],
      "settings": {
        "query": {
          "posts_per_page": "6"
        },
        "tag": "li",
        "_cssGlobalClasses": [
          "bvywvo"
        ]
      },
      "label": "Card wrapper"
    },
    {
      "id": "lgytwl",
      "name": "block",
      "parent": "tbbgmu",
      "children": [
        "trhbee",
        "fafuee"
      ],
      "settings": {
        "_cssGlobalClasses": [
          "uihqhz"
        ],
        "query": {
          "posts_per_page": "6"
        },
        "tag": "article"
      },
      "label": "Card"
    },
    {
      "id": "trhbee",
      "name": "block",
      "parent": "lgytwl",
      "children": [
        "jdkgem",
        "rmnwsn"
      ],
      "settings": {
        "_cssGlobalClasses": [
          "bzdwqo"
        ]
      },
      "label": "Container info"
    },
    {
      "id": "jdkgem",
      "name": "heading",
      "parent": "trhbee",
      "children": [],
      "settings": {
        "text": "Lorem ipsum",
        "_cssGlobalClasses": [
          "ykpeax"
        ],
        "tag": "h3"
      }
    },
    {
      "id": "rmnwsn",
      "name": "text",
      "parent": "trhbee",
      "children": [],
      "settings": {
        "text": "<p>Eos laudantium repellat sed architecto earum unde incidunt. Illum sit dolores voluptatem.</p>",
        "_cssGlobalClasses": [
          "ddiafu"
        ]
      },
      "label": "Description"
    },
    {
      "id": "fafuee",
      "name": "button",
      "parent": "lgytwl",
      "children": [],
      "settings": {
        "text": "Learn more",
        "_cssGlobalClasses": [
          "vkkdks"
        ],
        "link": {
          "type": "external",
          "url": "#"
        },
        "icon": {
          "library": "fontawesomeSolid",
          "icon": "fas fa-arrow-right"
        },
        "style": "dark"
      }
    },
    {
      "id": "frrbdn",
      "name": "container",
      "parent": "atljzi",
      "children": [
        "cobdzo",
        "sdeqcm"
      ],
      "settings": {
        "_cssGlobalClasses": [
          "hgirna"
        ]
      }
    },
    {
      "id": "cobdzo",
      "name": "block",
      "parent": "frrbdn",
      "children": [
        "gcjhks",
        "mqpscq",
        "kcifzh"
      ],
      "settings": {
        "_cssGlobalClasses": [
          "kwvafa"
        ]
      },
      "label": "Container info"
    },
    {
      "id": "gcjhks",
      "name": "text-basic",
      "parent": "cobdzo",
      "children": [],
      "settings": {
        "text": "Tagline",
        "tag": "p",
        "_cssGlobalClasses": [
          "awtnbm"
        ]
      },
      "label": "Tagline"
    },
    {
      "id": "mqpscq",
      "name": "heading",
      "parent": "cobdzo",
      "children": [],
      "settings": {
        "text": "Lorem ipsum dolor sit amet&nbsp;",
        "_cssGlobalClasses": [
          "qtzxkq"
        ],
        "tag": "h2"
      }
    },
    {
      "id": "kcifzh",
      "name": "text-basic",
      "parent": "cobdzo",
      "children": [],
      "settings": {
        "text": "Lorem ipsum dolor sit amet, consectetur adipiscing elit, sed do eiusmod tempor incididunt.",
        "tag": "p",
        "_cssGlobalClasses": [
          "xwuvmn"
        ]
      },
      "label": "Description"
    },
    {
      "id": "bcyeyq",
      "name": "div",
      "parent": "atljzi",
      "children": [],
      "settings": {
        "_cssGlobalClasses": [
          "ghlbpr"
        ]
      },
      "label": "Background overlap"
    }
  ],
  "source": "bricksCopiedElements",
  "sourceUrl": "https://cf.brixies.co",
  "version": "1.10.3",
  "globalClasses": [
    {
      "id": "qmfqfu",
      "name": "feature-61",
      "settings": {
        "_position": "relative",
        "_isolation": "isolate"
      }
    },
    {
      "id": "axqpwz",
      "name": "feature-61__grid",
      "settings": {
        "_margin": {
          "top": "0",
          "bottom": "0"
        },
        "_display": "grid",
        "_gridTemplateColumns": "repeat(3, minmax(0, 1fr))",
        "_padding": {
          "left": "0"
        },
        "_gridTemplateColumns:mobile_landscape": "repeat(1, minmax(0, 1fr))",
        "_gridGap": "var(--space-m)",
        "_gridTemplateRows": "repeat(1, minmax(0, 1fr))",
        "_alignItemsGrid": "stretch",
        "_gridGap:tablet_portrait": "var(--space-s)"
      }
    },
    {
      "id": "bvywvo",
      "name": "card-feature-61__wrapper",
      "settings": {}
    },
    {
      "id": "uihqhz",
      "name": "card-feature-61",
      "settings": {
        "_padding": {
          "top": "var(--space-l)",
          "right": "var(--space-l)",
          "bottom": "var(--space-l)",
          "left": "var(--space-l)"
        },
        "_display": "flex",
        "_direction": "column",
        "_background": {
          "color": {
            "raw": "var(--light)",
            "id": "01H7XJZ0KTXZ00FKVG3Y345XCP",
            "name": "light"
          }
        },
        "_border": {
          "width": {
            "top": "1",
            "right": "1",
            "bottom": "1",
            "left": "1"
          },
          "style": "solid",
          "color": {
            "raw": "var(--dark)",
            "id": "01H7XJZ4GBR5DD6Q0547QE5P4H",
            "name": "dark"
          }
        },
        "_rowGap": "var(--space-m)",
        "_padding:tablet_portrait": {
          "top": "var(--space-m)",
          "right": "var(--space-m)",
          "bottom": "var(--space-m)",
          "left": "var(--space-m)"
        },
        "_height": "100%"
      },
      "modified": 1721769392,
      "user_id": 2
    },
    {
      "id": "bzdwqo",
      "name": "card-feature-61__container-info",
      "settings": {
        "_rowGap": "var(--space-xs)"
      }
    },
    {
      "id": "ykpeax",
      "name": "card-feature-61__heading",
      "settings": {
        "_typography": {
          "font-size": "var(--text-l)",
          "font-weight": "700"
        }
      }
    },
    {
      "id": "ddiafu",
      "name": "card-feature-61__description",
      "settings": {}
    },
    {
      "id": "vkkdks",
      "name": "card-feature-61__btn",
      "settings": {
        "_margin": {
          "top": "auto"
        }
      }
    },
    {
      "id": "hgirna",
      "name": "feature-61__container",
      "settings": {
        "_rowGap": "var(--space-xl)",
        "_alignItems": "center"
      }
    },
    {
      "id": "kwvafa",
      "name": "feature-61__container-info",
      "settings": {
        "_alignItems": "center",
        "_rowGap": "var(--space-xs)",
        "_widthMax": "1080"
      }
    },
    {
      "id": "awtnbm",
      "name": "feature-61__tagline",
      "settings": {
        "_typography": {
          "font-weight": "600",
          "color": {
            "raw": "var(--light)",
            "id": "01H7XJZ0KTXZ00FKVG3Y345XCP",
            "name": "light"
          }
        },
        "_margin": {
          "bottom": "0"
        }
      }
    },
    {
      "id": "qtzxkq",
      "name": "feature-61__heading",
      "settings": {
        "_typography": {
          "font-size": "var(--text-2xl)",
          "text-align": "center",
          "color": {
            "raw": "var(--light)",
            "id": "01H7XJZ0KTXZ00FKVG3Y345XCP",
            "name": "light"
          }
        }
      }
    },
    {
      "id": "xwuvmn",
      "name": "feature-61__description",
      "settings": {
        "_typography": {
          "text-align": "center",
          "color": {
            "raw": "var(--light-80)",
            "id": "01H7XJZ0KTXZ00FKVG3Y345XCP.80",
            "name": "light-80"
          }
        },
        "_widthMax": "540"
      }
    },
    {
      "id": "ghlbpr",
      "name": "feature-61__bg",
      "settings": {
        "_background": {
          "color": {
            "raw": "var(--dark)",
            "id": "01H7XJZ4GBR5DD6Q0547QE5P4H",
            "name": "dark"
          }
        },
        "_width": "100%",
        "_height": "65%",
        "_position": "absolute",
        "_top": "0",
        "_right": "0",
        "_zIndex": "-1"
      }
    }
  ],
  "globalElements": []
}