{
  "content": [
    {
      "id": "mcaxah",
      "name": "section",
      "parent": 0,
      "children": [
        "ejrdvp"
      ],
      "settings": {
        "_cssGlobalClasses": [
          "pkwgpu"
        ]
      },
      "label": "Feature"
    },
    {
      "id": "ejrdvp",
      "name": "container",
      "parent": "mcaxah",
      "children": [
        "funbai",
        "jrpxqs"
      ],
      "settings": {
        "_cssGlobalClasses": [
          "oljxcn"
        ]
      }
    },
    {
      "id": "funbai",
      "name": "block",
      "parent": "ejrdvp",
      "children": [
        "szxlbt",
        "exfgxk",
        "mqyckk",
        "kdyiok"
      ],
      "settings": {
        "_cssGlobalClasses": [
          "gfnesb"
        ]
      },
      "label": "Container info"
    },
    {
      "id": "jrpxqs",
      "name": "image",
      "parent": "ejrdvp",
      "children": [],
      "settings": {
        "_cssGlobalClasses": [
          "pdyewh"
        ],
        "image": {
          "url": "https://acss.brixies.co/wp-content/uploads/2023/10/Placeholder-imagen-1-1.png",
          "external": true,
          "filename": "Placeholder-imagen-1-1.png"
        },
        "tag": "figure"
      },
      "themeStyles": []
    },
    {
      "id": "szxlbt",
      "name": "text-basic",
      "parent": "funbai",
      "children": [],
      "settings": {
        "text": "Tagline",
        "tag": "p",
        "_cssGlobalClasses": [
          "otybfx"
        ]
      },
      "label": "Tagline"
    },
    {
      "id": "exfgxk",
      "name": "heading",
      "parent": "funbai",
      "children": [],
      "settings": {
        "text": "Lorem ipsum",
        "_cssGlobalClasses": [
          "zfofpm"
        ]
      }
    },
    {
      "id": "mqyckk",
      "name": "text",
      "parent": "funbai",
      "children": [],
      "settings": {
        "text": "<p>Aliqua id fugiat nostrud irure ex duis ea quis id quis ad et. Sunt qui esse pariatur duis deserunt mollit dolore cillum minim tempor enim elit aute irure tempor cupidatat incididunt.</p>",
        "_cssGlobalClasses": [
          "fgggzq"
        ]
      },
      "label": "Description"
    },
    {
      "id": "kdyiok",
      "name": "block",
      "parent": "funbai",
      "children": [
        "sfuhlx",
        "fsovxf"
      ],
      "settings": {
        "_cssGlobalClasses": [
          "yideia"
        ]
      },
      "label": "Container button"
    },
    {
      "id": "sfuhlx",
      "name": "button",
      "parent": "kdyiok",
      "children": [],
      "settings": {
        "text": "Contact",
        "_cssGlobalClasses": [
          "czcbqk"
        ],
        "link": {
          "type": "external",
          "url": "#"
        },
        "style": "primary"
      },
      "label": "Button primary"
    },
    {
      "id": "fsovxf",
      "name": "button",
      "parent": "kdyiok",
      "children": [],
      "settings": {
        "text": "See more",
        "_cssGlobalClasses": [
          "rflila"
        ],
        "icon": {
          "library": "fontawesomeSolid",
          "icon": "fas fa-arrow-right"
        },
        "link": {
          "type": "external",
          "url": "#"
        }
      },
      "label": "Button inline"
    }
  ],
  "source": "bricksCopiedElements",
  "sourceUrl": "https://cf.brixies.co",
  "version": "1.9.9",
  "globalClasses": [
    {
      "id": "pkwgpu",
      "name": "feature-3",
      "settings": [],
      "modified": 1721783952,
      "user_id": 2
    },
    {
      "id": "oljxcn",
      "name": "feature-3__container",
      "settings": {
        "_direction:mobile_landscape": "column",
        "_rowGap:mobile_landscape": "var(--space-l)",
        "_display": "grid",
        "_gridGap": "var(--space-m)",
        "_gridTemplateColumns": "repeat(2, minmax(0, 1fr))",
        "_alignItemsGrid": "center",
        "_gridGap:tablet_portrait": "var(--space-s)",
        "_gridTemplateColumns:mobile_landscape": "repeat(1, minmax(0, 1fr))",
        "_gridGap:mobile_landscape": "var(--space-l)"
      }
    },
    {
      "id": "gfnesb",
      "name": "feature-3__info-container",
      "settings": {
        "_width:mobile_landscape": "100%"
      }
    },
    {
      "id": "pdyewh",
      "name": "feature-3__img",
      "settings": {
        "_border": {
          "radius": {
            "top": "var(--radius-m)",
            "right": "var(--radius-m)",
            "bottom": "var(--radius-m)",
            "left": "var(--radius-m)"
          }
        },
        "_width:mobile_landscape": "100%",
        "_overflow": "hidden"
      }
    },
    {
      "id": "otybfx",
      "name": "feature-3__tagline",
      "settings": {
        "_typography": {
          "color": {
            "raw": "var(--dark)",
            "id": "01H7XJZ4GBR5DD6Q0547QE5P4H",
            "name": "dark"
          },
          "font-size": "var(--text-m)",
          "font-weight": "600"
        }
      }
    },
    {
      "id": "zfofpm",
      "name": "feature-3__heading",
      "settings": {
        "_typography": {
          "font-size": "var(--text-2xl)"
        },
        "_margin": {
          "top": "var(--space-xs)"
        }
      }
    },
    {
      "id": "fgggzq",
      "name": "feature-3__description",
      "settings": {
        "_margin": {
          "top": "var(--space-m)"
        }
      }
    },
    {
      "id": "yideia",
      "name": "feature-3__btn-container",
      "settings": {
        "_margin": {
          "top": "var(--space-m)"
        },
        "_direction": "row",
        "_columnGap": "var(--space-m)",
        "_flexWrap": "nowrap",
        "_alignItems": "center"
      }
    },
    {
      "id": "czcbqk",
      "name": "feature-3__btn--primary",
      "settings": {
        "_padding:mobile_landscape": {
          "bottom": "var(--space-s)",
          "top": "var(--space-s)"
        }
      }
    },
    {
      "id": "rflila",
      "name": "feature-3__btn-inline",
      "settings": {
        "_padding": {
          "top": "0",
          "bottom": "0",
          "left": "0",
          "right": "0"
        },
        "_typography": {
          "font-size": "var(--text-s)"
        },
        "_flexDirection": "row",
        "_alignItems": "center"
      }
    }
  ],
  "globalElements": []
}