{
  "content": [
    {
      "id": "pejbyk",
      "name": "section",
      "parent": 0,
      "children": [
        "zrpgax"
      ],
      "settings": {
        "_cssGlobalClasses": [
          "dokzej"
        ],
        "query": {
          "posts_per_page": "1",
          "offset": "1"
        }
      },
      "label": "Hero"
    },
    {
      "id": "zrpgax",
      "name": "container",
      "parent": "pejbyk",
      "children": [
        "fizjbv",
        "fiinpr",
        "tdrqmg"
      ],
      "settings": {
        "_cssGlobalClasses": [
          "phjrae"
        ]
      }
    },
    {
      "id": "fizjbv",
      "name": "breadcrumbs",
      "parent": "zrpgax",
      "children": [],
      "settings": {
        "separatorType": "icon",
        "separatorIcon": {
          "library": "fontawesomeSolid",
          "icon": "fas fa-angle-right"
        },
        "_cssGlobalClasses": [
          "nznski"
        ]
      },
      "themeStyles": {}
    },
    {
      "id": "fiinpr",
      "name": "block",
      "parent": "zrpgax",
      "children": [
        "xopgpr",
        "lemcoh"
      ],
      "settings": {
        "_cssGlobalClasses": [
          "ingjhd"
        ]
      },
      "label": "Container info"
    },
    {
      "id": "xopgpr",
      "name": "post-title",
      "parent": "fiinpr",
      "children": [],
      "settings": {
        "tag": "h1",
        "_cssGlobalClasses": [
          "yjhlfd"
        ]
      },
      "themeStyles": {}
    },
    {
      "id": "lemcoh",
      "name": "post-excerpt",
      "parent": "fiinpr",
      "children": [],
      "settings": {
        "length": "99",
        "_cssGlobalClasses": [
          "muzfne"
        ]
      },
      "themeStyles": {}
    },
    {
      "id": "tdrqmg",
      "name": "block",
      "parent": "zrpgax",
      "children": [
        "rcixom",
        "xtwqjk",
        "oavyne"
      ],
      "settings": {
        "_cssGlobalClasses": [
          "bpjkjz"
        ]
      },
      "label": "Image wrapper"
    },
    {
      "id": "rcixom",
      "name": "image",
      "parent": "tdrqmg",
      "children": [],
      "settings": {
        "tag": "figure",
        "_cssGlobalClasses": [
          "jpbazn"
        ],
        "image": {
          "url": "https://acss.brixies.co/wp-content/uploads/2023/10/Img-placeholder-16-9.png",
          "external": true,
          "filename": "Img-placeholder-16-9.png"
        }
      },
      "label": "Featured image",
      "themeStyles": {}
    },
    {
      "id": "xtwqjk",
      "name": "div",
      "parent": "tdrqmg",
      "children": [],
      "settings": {
        "_cssGlobalClasses": [
          "bosblk"
        ]
      },
      "label": "Overlay gradient"
    },
    {
      "id": "oavyne",
      "name": "block",
      "parent": "tdrqmg",
      "children": [
        "npmvvz",
        "dcngmj"
      ],
      "settings": {
        "_cssGlobalClasses": [
          "kztfrz"
        ],
        "tag": "ul"
      },
      "label": "Metadata"
    },
    {
      "id": "npmvvz",
      "name": "block",
      "parent": "oavyne",
      "children": [
        "duuqhx",
        "qtsotp"
      ],
      "settings": {
        "_cssGlobalClasses": [
          "glgydy"
        ],
        "tag": "li"
      },
      "label": "Metadata container"
    },
    {
      "id": "duuqhx",
      "name": "heading",
      "parent": "npmvvz",
      "children": [],
      "settings": {
        "text": "Written by",
        "tag": "h3",
        "_cssGlobalClasses": [
          "fzwzpz"
        ]
      }
    },
    {
      "id": "qtsotp",
      "name": "text-basic",
      "parent": "npmvvz",
      "children": [],
      "settings": {
        "tag": "p",
        "_cssGlobalClasses": [
          "iigrno"
        ],
        "text": "Smith Benites",
        "link": {
          "type": "meta",
          "useDynamicData": "#"
        }
      },
      "label": "Author name"
    },
    {
      "id": "dcngmj",
      "name": "block",
      "parent": "oavyne",
      "children": [
        "xhbiii",
        "tprrsy"
      ],
      "settings": {
        "_cssGlobalClasses": [
          "glgydy"
        ],
        "tag": "li"
      },
      "label": "Metadata container"
    },
    {
      "id": "xhbiii",
      "name": "heading",
      "parent": "dcngmj",
      "children": [],
      "settings": {
        "text": "Published on",
        "tag": "h3",
        "_cssGlobalClasses": [
          "fzwzpz"
        ]
      }
    },
    {
      "id": "tprrsy",
      "name": "text-basic",
      "parent": "dcngmj",
      "children": [],
      "settings": {
        "tag": "custom",
        "_cssGlobalClasses": [
          "iigrno"
        ],
        "text": "February 22, 2024",
        "customTag": "time"
      },
      "label": "Post date"
    }
  ],
  "source": "bricksCopiedElements",
  "sourceUrl": "https://cf.brixies.co",
  "version": "1.10.3",
  "globalClasses": [
    {
      "id": "dokzej",
      "name": "single-post-hero-4",
      "settings": {}
    },
    {
      "id": "phjrae",
      "name": "single-post-hero-4__container",
      "settings": {
        "_width": "1080",
        "_rowGap": "var(--space-xl)"
      }
    },
    {
      "id": "nznski",
      "name": "single-post-hero-4__breadcrumbs",
      "settings": {
        "itemTypography": {
          "color": {
            "raw": "var(--dark)",
            "id": "01H7XJZ4GBR5DD6Q0547QE5P4H",
            "name": "dark"
          }
        },
        "currentItemTypography": {
          "color": {
            "raw": "var(--dark)",
            "id": "01H7XJZ4GBR5DD6Q0547QE5P4H",
            "name": "dark"
          }
        },
        "gap": ".625em",
        "separatorColor": {
          "raw": "var(--dark)",
          "id": "01H7XJZ4GBR5DD6Q0547QE5P4H",
          "name": "dark"
        }
      }
    },
    {
      "id": "ingjhd",
      "name": "single-post-hero-4__container-info",
      "settings": {
        "_direction": "column",
        "_rowGap": "var(--space-xs)"
      }
    },
    {
      "id": "yjhlfd",
      "name": "single-post-hero-4__title",
      "settings": {
        "_typography": {
          "font-size": "var(--text-2xl)"
        }
      }
    },
    {
      "id": "muzfne",
      "name": "single-post-hero-4__excerpt",
      "settings": {}
    },
    {
      "id": "bpjkjz",
      "name": "single-post-hero-4__img-wrapper",
      "settings": {
        "_position": "relative",
        "_aspectRatio": "16 / 9",
        "_isolation": "isolate",
        "_padding": {
          "top": "var(--space-m)",
          "right": "var(--space-m)",
          "bottom": "var(--space-m)",
          "left": "var(--space-m)"
        },
        "_alignItems": "flex-start",
        "_justifyContent": "flex-end",
        "_aspectRatio:mobile_portrait": "1"
      }
    },
    {
      "id": "jpbazn",
      "name": "single-post-hero-4__img",
      "settings": {
        "_objectFit": "cover",
        "_objectPosition": "50%",
        "_position": "absolute",
        "_top": "0",
        "_right": "0",
        "_zIndex": "-1",
        "_width": "100%",
        "_height": "100%"
      }
    },
    {
      "id": "bosblk",
      "name": "single-post-hero-4__overlay-gradient",
      "settings": {
        "_width": "100%",
        "_height": "100%",
        "_position": "absolute",
        "_top": "0",
        "_right": "0",
        "_zIndex": "-1",
        "_gradient": {
          "applyTo": "background",
          "colors": [
            {
              "id": "jdcujg",
              "stop": "50",
              "color": {
                "raw": "transparent"
              }
            },
            {
              "id": "gnrhvz",
              "stop": "100%",
              "color": {
                "raw": "var(--dark-40)",
                "id": "01H7XJZ4GBR5DD6Q0547QE5P4H.40",
                "name": "dark-40"
              }
            }
          ]
        }
      }
    },
    {
      "id": "kztfrz",
      "name": "single-post-hero-4__metadata",
      "settings": {
        "_direction": "row",
        "_columnGap": "var(--space-m)",
        "_alignItems": "center",
        "_justifyContent": "flex-start",
        "_flexWrap": "wrap",
        "_margin": {
          "top": "0",
          "bottom": "0"
        },
        "_padding": {
          "left": "0"
        }
      }
    },
    {
      "id": "glgydy",
      "name": "single-post-hero-4__meta-container",
      "settings": {
        "_rowGap": "var(--space-3xs)",
        "_width": "fit-content"
      }
    },
    {
      "id": "fzwzpz",
      "name": "single-post-hero-4__meta-heading",
      "settings": {
        "_typography": {
          "color": {
            "raw": "var(--light)",
            "id": "01H7XJZ0KTXZ00FKVG3Y345XCP",
            "name": "light"
          },
          "font-size": "var(--text-s)"
        }
      }
    },
    {
      "id": "iigrno",
      "name": "single-post-hero-4__meta-info",
      "settings": {
        "_typography": {
          "color": {
            "raw": "var(--light)",
            "id": "01H7XJZ0KTXZ00FKVG3Y345XCP",
            "name": "light"
          },
          "text-transform": "capitalize"
        }
      }
    }
  ],
  "globalElements": []
}