{
  "content": [
    {
      "id": "ilmfmh",
      "name": "section",
      "parent": 0,
      "children": [
        "ilteyi"
      ],
      "settings": {
        "_cssGlobalClasses": [
          "pjijnx"
        ]
      },
      "label": "Timeline"
    },
    {
      "id": "ilteyi",
      "name": "container",
      "parent": "ilmfmh",
      "children": [
        "bilokr",
        "xbmmdn"
      ],
      "settings": {
        "_cssGlobalClasses": [
          "rwkpqb"
        ]
      }
    },
    {
      "id": "bilokr",
      "name": "block",
      "parent": "ilteyi",
      "children": [
        "rxbsff",
        "twhipp",
        "lysaod"
      ],
      "settings": {
        "_cssGlobalClasses": [
          "eiqxzp"
        ]
      },
      "label": "Container info"
    },
    {
      "id": "rxbsff",
      "name": "text-basic",
      "parent": "bilokr",
      "children": [],
      "settings": {
        "text": "Tagline",
        "_cssGlobalClasses": [
          "luzdzi"
        ],
        "tag": "p"
      },
      "label": "Tagline"
    },
    {
      "id": "twhipp",
      "name": "heading",
      "parent": "bilokr",
      "children": [],
      "settings": {
        "text": "Lorem ipsum dolor sit amet&nbsp;",
        "tag": "h2",
        "_cssGlobalClasses": [
          "mgiuqp"
        ]
      }
    },
    {
      "id": "lysaod",
      "name": "text-basic",
      "parent": "bilokr",
      "children": [],
      "settings": {
        "tag": "p",
        "_cssGlobalClasses": [
          "xqavoa"
        ],
        "text": "Lorem ipsum dolor sit amet, consectetur adipiscing elit, sed do eiusmod tempor incididunt."
      },
      "label": "Description"
    },
    {
      "id": "nldsjd",
      "name": "slider-nested",
      "parent": "xbmmdn",
      "children": [
        "xkewwp",
        "bqktah",
        "donjuq",
        "pzhqnc"
      ],
      "settings": {
        "_cssGlobalClasses": [
          "yedmrs"
        ],
        "perPage": "3",
        "height": "auto",
        "gap": "var(--space-m)",
        "perPage:tablet_portrait": "2",
        "perPage:mobile_portrait": "1",
        "arrows": true,
        "prevArrow": {
          "library": "fontawesomeSolid",
          "icon": "fas fa-arrow-left"
        },
        "nextArrow": {
          "library": "fontawesomeSolid",
          "icon": "fas fa-arrow-right"
        },
        "gap:tablet_portrait": "var(--space-s)"
      },
      "label": "Slider",
      "themeStyles": []
    },
    {
      "id": "xqzrcn",
      "name": "block",
      "parent": "xkewwp",
      "children": [
        "ecdiyn",
        "pmdeym",
        "fqfbbw"
      ],
      "settings": {
        "_cssGlobalClasses": [
          "fmlhdk"
        ],
        "tag": "div"
      },
      "label": "Column"
    },
    {
      "id": "ecdiyn",
      "name": "block",
      "parent": "xqzrcn",
      "children": [
        "mfoabw"
      ],
      "settings": {
        "_cssGlobalClasses": [
          "jkfqum"
        ]
      },
      "label": "Image wrapper"
    },
    {
      "id": "mfoabw",
      "name": "image",
      "parent": "ecdiyn",
      "children": [],
      "settings": {
        "_cssGlobalClasses": [
          "mcvcpp"
        ],
        "image": {
          "url": "https://acss.brixies.co/wp-content/uploads/2023/10/Img-placeholder-16-9.png",
          "external": true,
          "filename": "Img-placeholder-16-9.png"
        },
        "tag": "figure"
      },
      "themeStyles": []
    },
    {
      "id": "pmdeym",
      "name": "block",
      "parent": "xqzrcn",
      "children": [
        "fubain"
      ],
      "settings": {
        "_cssGlobalClasses": [
          "bqniin"
        ]
      },
      "label": "Icon wrapper"
    },
    {
      "id": "fubain",
      "name": "icon",
      "parent": "pmdeym",
      "children": [],
      "settings": {
        "icon": {
          "library": "fontawesomeSolid",
          "icon": "fas fa-circle"
        },
        "_cssGlobalClasses": [
          "cqaflm"
        ]
      },
      "themeStyles": []
    },
    {
      "id": "fqfbbw",
      "name": "block",
      "parent": "xqzrcn",
      "children": [
        "ibkscd",
        "fuuuko"
      ],
      "settings": {
        "_cssGlobalClasses": [
          "qhfqse"
        ]
      },
      "label": "Content"
    },
    {
      "id": "ibkscd",
      "name": "block",
      "parent": "fqfbbw",
      "children": [
        "ztbtbq",
        "rbofsp"
      ],
      "settings": {
        "_cssGlobalClasses": [
          "dlccwl"
        ]
      },
      "label": "Container"
    },
    {
      "id": "ztbtbq",
      "name": "text-basic",
      "parent": "ibkscd",
      "children": [],
      "settings": {
        "text": "2022",
        "tag": "custom",
        "customTag": "time",
        "_cssGlobalClasses": [
          "iotdrz"
        ]
      },
      "label": "Date"
    },
    {
      "id": "rbofsp",
      "name": "heading",
      "parent": "ibkscd",
      "children": [],
      "settings": {
        "text": "Lorem ipsum dolor",
        "_cssGlobalClasses": [
          "cwdcot"
        ]
      }
    },
    {
      "id": "fuuuko",
      "name": "text",
      "parent": "fqfbbw",
      "children": [],
      "settings": {
        "_cssGlobalClasses": [
          "wpdrer"
        ],
        "text": "<p>Lorem ipsum dolor sit amet, consectetur adipiscing elit lobortis arcu enim urna adipiscing praesent velit viverra sit semper lorem.</p>"
      },
      "label": "Description"
    },
    {
      "id": "xbmmdn",
      "name": "block",
      "parent": "ilteyi",
      "children": [
        "nldsjd",
        "vzfbxs"
      ],
      "settings": {
        "_cssGlobalClasses": [
          "omepxz"
        ]
      },
      "label": "Slider wrapper"
    },
    {
      "id": "xkewwp",
      "name": "block",
      "parent": "nldsjd",
      "children": [
        "xqzrcn"
      ],
      "settings": {
        "_cssGlobalClasses": [
          "ibkplr"
        ]
      },
      "label": "Column Wrapper"
    },
    {
      "id": "pzhqnc",
      "name": "block",
      "parent": "nldsjd",
      "children": [
        "duapvt"
      ],
      "settings": {
        "_cssGlobalClasses": [
          "ibkplr"
        ]
      },
      "label": "Column Wrapper"
    },
    {
      "id": "duapvt",
      "name": "block",
      "parent": "pzhqnc",
      "children": [
        "rkumgc",
        "zmimsr",
        "jrvnum"
      ],
      "settings": {
        "_cssGlobalClasses": [
          "fmlhdk"
        ],
        "tag": "div"
      },
      "label": "Column"
    },
    {
      "id": "rkumgc",
      "name": "block",
      "parent": "duapvt",
      "children": [
        "fepsni"
      ],
      "settings": {
        "_cssGlobalClasses": [
          "jkfqum"
        ]
      },
      "label": "Image wrapper"
    },
    {
      "id": "fepsni",
      "name": "image",
      "parent": "rkumgc",
      "children": [],
      "settings": {
        "_cssGlobalClasses": [
          "mcvcpp"
        ],
        "image": {
          "url": "https://acss.brixies.co/wp-content/uploads/2023/10/Img-placeholder-16-9.png",
          "external": true,
          "filename": "Img-placeholder-16-9.png"
        },
        "tag": "figure"
      },
      "themeStyles": []
    },
    {
      "id": "zmimsr",
      "name": "block",
      "parent": "duapvt",
      "children": [
        "unvhbv"
      ],
      "settings": {
        "_cssGlobalClasses": [
          "bqniin"
        ]
      },
      "label": "Icon wrapper"
    },
    {
      "id": "unvhbv",
      "name": "icon",
      "parent": "zmimsr",
      "children": [],
      "settings": {
        "icon": {
          "library": "fontawesomeSolid",
          "icon": "fas fa-circle"
        },
        "_cssGlobalClasses": [
          "cqaflm"
        ]
      },
      "themeStyles": []
    },
    {
      "id": "jrvnum",
      "name": "block",
      "parent": "duapvt",
      "children": [
        "dqoneq",
        "iyeidn"
      ],
      "settings": {
        "_cssGlobalClasses": [
          "qhfqse"
        ]
      },
      "label": "Content"
    },
    {
      "id": "dqoneq",
      "name": "block",
      "parent": "jrvnum",
      "children": [
        "mbnenn",
        "mvsptr"
      ],
      "settings": {
        "_cssGlobalClasses": [
          "dlccwl"
        ]
      },
      "label": "Container"
    },
    {
      "id": "mbnenn",
      "name": "text-basic",
      "parent": "dqoneq",
      "children": [],
      "settings": {
        "text": "2025",
        "tag": "custom",
        "customTag": "time",
        "_cssGlobalClasses": [
          "iotdrz"
        ]
      },
      "label": "Date"
    },
    {
      "id": "mvsptr",
      "name": "heading",
      "parent": "dqoneq",
      "children": [],
      "settings": {
        "text": "Lorem ipsum dolor",
        "_cssGlobalClasses": [
          "cwdcot"
        ]
      }
    },
    {
      "id": "iyeidn",
      "name": "text",
      "parent": "jrvnum",
      "children": [],
      "settings": {
        "_cssGlobalClasses": [
          "wpdrer"
        ],
        "text": "<p>Lorem ipsum dolor sit amet, consectetur adipiscing elit lobortis arcu enim urna adipiscing praesent velit viverra sit semper lorem.</p>"
      },
      "label": "Description"
    },
    {
      "id": "donjuq",
      "name": "block",
      "parent": "nldsjd",
      "children": [
        "zxzyuk"
      ],
      "settings": {
        "_cssGlobalClasses": [
          "ibkplr"
        ]
      },
      "label": "Column Wrapper"
    },
    {
      "id": "zxzyuk",
      "name": "block",
      "parent": "donjuq",
      "children": [
        "mrhwlw",
        "uyltpj",
        "kmzyvm"
      ],
      "settings": {
        "_cssGlobalClasses": [
          "fmlhdk"
        ],
        "tag": "div"
      },
      "label": "Column"
    },
    {
      "id": "mrhwlw",
      "name": "block",
      "parent": "zxzyuk",
      "children": [
        "zzvinw"
      ],
      "settings": {
        "_cssGlobalClasses": [
          "jkfqum"
        ]
      },
      "label": "Image wrapper"
    },
    {
      "id": "zzvinw",
      "name": "image",
      "parent": "mrhwlw",
      "children": [],
      "settings": {
        "_cssGlobalClasses": [
          "mcvcpp"
        ],
        "image": {
          "url": "https://acss.brixies.co/wp-content/uploads/2023/10/Img-placeholder-16-9.png",
          "external": true,
          "filename": "Img-placeholder-16-9.png"
        },
        "tag": "figure"
      },
      "themeStyles": []
    },
    {
      "id": "uyltpj",
      "name": "block",
      "parent": "zxzyuk",
      "children": [
        "ukycju"
      ],
      "settings": {
        "_cssGlobalClasses": [
          "bqniin"
        ]
      },
      "label": "Icon wrapper"
    },
    {
      "id": "ukycju",
      "name": "icon",
      "parent": "uyltpj",
      "children": [],
      "settings": {
        "icon": {
          "library": "fontawesomeSolid",
          "icon": "fas fa-circle"
        },
        "_cssGlobalClasses": [
          "cqaflm"
        ]
      },
      "themeStyles": []
    },
    {
      "id": "kmzyvm",
      "name": "block",
      "parent": "zxzyuk",
      "children": [
        "fsipzp",
        "dsujam"
      ],
      "settings": {
        "_cssGlobalClasses": [
          "qhfqse"
        ]
      },
      "label": "Content"
    },
    {
      "id": "fsipzp",
      "name": "block",
      "parent": "kmzyvm",
      "children": [
        "ximjqr",
        "ojlvuy"
      ],
      "settings": {
        "_cssGlobalClasses": [
          "dlccwl"
        ]
      },
      "label": "Container"
    },
    {
      "id": "ximjqr",
      "name": "text-basic",
      "parent": "fsipzp",
      "children": [],
      "settings": {
        "text": "2024",
        "tag": "custom",
        "customTag": "time",
        "_cssGlobalClasses": [
          "iotdrz"
        ]
      },
      "label": "Date"
    },
    {
      "id": "ojlvuy",
      "name": "heading",
      "parent": "fsipzp",
      "children": [],
      "settings": {
        "text": "Lorem ipsum dolor",
        "_cssGlobalClasses": [
          "cwdcot"
        ]
      }
    },
    {
      "id": "dsujam",
      "name": "text",
      "parent": "kmzyvm",
      "children": [],
      "settings": {
        "_cssGlobalClasses": [
          "wpdrer"
        ],
        "text": "<p>Lorem ipsum dolor sit amet, consectetur adipiscing elit lobortis arcu enim urna adipiscing praesent velit viverra sit semper lorem.</p>"
      },
      "label": "Description"
    },
    {
      "id": "bqktah",
      "name": "block",
      "parent": "nldsjd",
      "children": [
        "tbkmcx"
      ],
      "settings": {
        "_cssGlobalClasses": [
          "ibkplr"
        ]
      },
      "label": "Column Wrapper"
    },
    {
      "id": "tbkmcx",
      "name": "block",
      "parent": "bqktah",
      "children": [
        "uysawv",
        "ommvog",
        "otnyaj"
      ],
      "settings": {
        "_cssGlobalClasses": [
          "fmlhdk"
        ],
        "tag": "div"
      },
      "label": "Column"
    },
    {
      "id": "uysawv",
      "name": "block",
      "parent": "tbkmcx",
      "children": [
        "qpspkg"
      ],
      "settings": {
        "_cssGlobalClasses": [
          "jkfqum"
        ]
      },
      "label": "Image wrapper"
    },
    {
      "id": "qpspkg",
      "name": "image",
      "parent": "uysawv",
      "children": [],
      "settings": {
        "_cssGlobalClasses": [
          "mcvcpp"
        ],
        "image": {
          "url": "https://acss.brixies.co/wp-content/uploads/2023/10/Img-placeholder-16-9.png",
          "external": true,
          "filename": "Img-placeholder-16-9.png"
        },
        "tag": "figure"
      },
      "themeStyles": []
    },
    {
      "id": "ommvog",
      "name": "block",
      "parent": "tbkmcx",
      "children": [
        "ohmfqj"
      ],
      "settings": {
        "_cssGlobalClasses": [
          "bqniin"
        ]
      },
      "label": "Icon wrapper"
    },
    {
      "id": "ohmfqj",
      "name": "icon",
      "parent": "ommvog",
      "children": [],
      "settings": {
        "icon": {
          "library": "fontawesomeSolid",
          "icon": "fas fa-circle"
        },
        "_cssGlobalClasses": [
          "cqaflm"
        ]
      },
      "themeStyles": []
    },
    {
      "id": "otnyaj",
      "name": "block",
      "parent": "tbkmcx",
      "children": [
        "zwaoql",
        "jpabzz"
      ],
      "settings": {
        "_cssGlobalClasses": [
          "qhfqse"
        ]
      },
      "label": "Content"
    },
    {
      "id": "zwaoql",
      "name": "block",
      "parent": "otnyaj",
      "children": [
        "fqupis",
        "zzswpp"
      ],
      "settings": {
        "_cssGlobalClasses": [
          "dlccwl"
        ]
      },
      "label": "Container"
    },
    {
      "id": "fqupis",
      "name": "text-basic",
      "parent": "zwaoql",
      "children": [],
      "settings": {
        "text": "2023",
        "tag": "custom",
        "customTag": "time",
        "_cssGlobalClasses": [
          "iotdrz"
        ]
      },
      "label": "Date"
    },
    {
      "id": "zzswpp",
      "name": "heading",
      "parent": "zwaoql",
      "children": [],
      "settings": {
        "text": "Lorem ipsum dolor",
        "_cssGlobalClasses": [
          "cwdcot"
        ]
      }
    },
    {
      "id": "jpabzz",
      "name": "text",
      "parent": "otnyaj",
      "children": [],
      "settings": {
        "_cssGlobalClasses": [
          "wpdrer"
        ],
        "text": "<p>Lorem ipsum dolor sit amet, consectetur adipiscing elit lobortis arcu enim urna adipiscing praesent velit viverra sit semper lorem.</p>"
      },
      "label": "Description"
    },
    {
      "id": "vzfbxs",
      "name": "divider",
      "parent": "xbmmdn",
      "children": [],
      "settings": {
        "_cssGlobalClasses": [
          "bhkjoc"
        ],
        "direction": "horizontal"
      },
      "label": "Line",
      "themeStyles": []
    }
  ],
  "source": "bricksCopiedElements",
  "sourceUrl": "https://cf.brixies.co",
  "version": "1.10.1",
  "globalClasses": [
    {
      "id": "pjijnx",
      "name": "timeline-4",
      "settings": {}
    },
    {
      "id": "rwkpqb",
      "name": "timeline-4__container",
      "settings": {
        "_direction": "column",
        "_alignItems": "center",
        "_rowGap": "var(--space-xl)"
      }
    },
    {
      "id": "eiqxzp",
      "name": "timeline-4__container-info",
      "settings": {
        "_alignItems": "center",
        "_rowGap": "var(--space-xs)",
        "_width": "1080"
      }
    },
    {
      "id": "luzdzi",
      "name": "timeline-4__tagline",
      "settings": {
        "_typography": {
          "font-weight": "600",
          "color": {
            "raw": "var(--dark)",
            "id": "01H7XJZ4GBR5DD6Q0547QE5P4H",
            "name": "dark"
          }
        },
        "_margin": {
          "bottom": "0"
        }
      }
    },
    {
      "id": "mgiuqp",
      "name": "timeline-4__heading",
      "settings": {
        "_typography": {
          "font-size": "var(--text-2xl)",
          "text-align": "center"
        }
      }
    },
    {
      "id": "xqavoa",
      "name": "timeline-4__description",
      "settings": {
        "_typography": {
          "text-align": "center"
        },
        "_widthMax": "540"
      }
    },
    {
      "id": "yedmrs",
      "name": "timeline-4__slider",
      "settings": {
        "arrowHeight": "4.5rem",
        "arrowWidth": "4.5rem",
        "arrowSize": "1.8rem",
        "arrowBackground": {
          "raw": "var(--light)",
          "id": "01H7XJZ0KTXZ00FKVG3Y345XCP",
          "name": "light"
        },
        "arrowBorder": {
          "radius": {
            "top": "var(--radius-xs)",
            "right": "var(--radius-xs)",
            "bottom": "var(--radius-xs)",
            "left": "var(--radius-xs)"
          },
          "width": {
            "top": "1",
            "right": "1",
            "bottom": "1",
            "left": "1"
          },
          "style": "solid",
          "color": {
            "raw": "var(--dark-20)",
            "id": "01H7XJZ4GBR5DD6Q0547QE5P4H.20",
            "name": "dark-20"
          }
        }
      },
      "modified": 1724281600,
      "user_id": 1
    },
    {
      "id": "fmlhdk",
      "name": "timeline-4__column",
      "settings": {
        "_display": "grid",
        "_gridGap": "var(--space-m)",
        "_isolation": "isolate",
        "_gridAutoFlow": "column",
        "_gridTemplateRows": "minmax(0, 1fr) max-content minmax(0, 1fr)",
        "_gridTemplateColumns": "repeat(1, minmax(0, 1fr))"
      },
      "modified": 1724280620,
      "user_id": 1
    },
    {
      "id": "jkfqum",
      "name": "timeline-4__img-wrapper",
      "settings": {
        "_justifyContent": "flex-end"
      }
    },
    {
      "id": "mcvcpp",
      "name": "timeline-4__img",
      "settings": {
        "_aspectRatio": "4 / 3",
        "_objectFit": "cover",
        "_objectPosition": "50%"
      }
    },
    {
      "id": "bqniin",
      "name": "timeline-4__icon-wrapper",
      "settings": {
        "_width": "fit-content",
        "_margin": {
          "left": "auto",
          "right": "auto"
        },
        "_padding": {
          "top": "var(--space-xs)",
          "right": "var(--space-xs)",
          "bottom": "var(--space-xs)",
          "left": "var(--space-xs)"
        },
        "_height": "fit-content",
        "_background": {
          "color": {
            "raw": "var(--light)",
            "id": "01H7XJZ0KTXZ00FKVG3Y345XCP",
            "name": "light"
          }
        }
      }
    },
    {
      "id": "cqaflm",
      "name": "timeline-4__icon",
      "settings": {
        "iconSize": "var(--text-l)",
        "iconColor": {
          "raw": "var(--dark)",
          "id": "01H7XJZ4GBR5DD6Q0547QE5P4H",
          "name": "dark"
        }
      }
    },
    {
      "id": "qhfqse",
      "name": "timeline-4__content",
      "settings": {
        "_rowGap": "var(--space-m)"
      }
    },
    {
      "id": "dlccwl",
      "name": "timeline-4__content-container",
      "settings": {
        "_rowGap": "var(--space-xs)",
        "_alignItems": "center"
      },
      "modified": 1724280747,
      "user_id": 1
    },
    {
      "id": "iotdrz",
      "name": "timeline-4__content-date",
      "settings": {
        "_typography": {
          "font-weight": "600",
          "color": {
            "raw": "var(--dark)",
            "id": "01H7XJZ4GBR5DD6Q0547QE5P4H",
            "name": "dark"
          },
          "line-height": "1.2",
          "text-align": "center"
        }
      },
      "modified": 1724280747,
      "user_id": 1
    },
    {
      "id": "cwdcot",
      "name": "timeline-4__content-heading",
      "settings": {
        "_typography": {
          "font-size": "var(--text-xl)",
          "text-align": "center"
        }
      },
      "modified": 1724280747,
      "user_id": 1
    },
    {
      "id": "wpdrer",
      "name": "timeline-4__content-description",
      "settings": {
        "_typography": {
          "text-align": "center"
        }
      }
    },
    {
      "id": "omepxz",
      "name": "timeline-4__slider-wrapper",
      "settings": {
        "_position": "relative",
        "_isolation": "isolate"
      }
    },
    {
      "id": "ibkplr",
      "name": "timeline-4__column-wrapper",
      "settings": {}
    },
    {
      "id": "bhkjoc",
      "name": "timeline-4__line",
      "settings": {
        "height": "2",
        "_transform": {
          "translateY": "-50%"
        },
        "_position": "absolute",
        "_top": "50%",
        "color": {
          "raw": "var(--dark)",
          "id": "01H7XJZ4GBR5DD6Q0547QE5P4H",
          "name": "dark"
        },
        "_order:mobile_landscape": "0",
        "width": "100%",
        "_zIndex": "-1",
        "_width": "100%"
      },
      "modified": 1724286470,
      "user_id": 2
    }
  ],
  "globalElements": []
}