{
  "content": [
    {
      "id": "parhek",
      "name": "section",
      "parent": 0,
      "children": [
        "kqpgmm",
        "bgtsvc"
      ],
      "settings": {
        "_cssGlobalClasses": [
          "pspsdj"
        ]
      },
      "label": "Hero"
    },
    {
      "id": "kqpgmm",
      "name": "container",
      "parent": "parhek",
      "children": [
        "ebgybg",
        "xtsstq"
      ],
      "settings": {
        "_cssGlobalClasses": [
          "kunmut"
        ]
      },
      "label": "Container"
    },
    {
      "id": "ebgybg",
      "name": "block",
      "parent": "kqpgmm",
      "children": [
        "imwush",
        "xbrytm",
        "qcuofw"
      ],
      "settings": {
        "_cssGlobalClasses": [
          "ntpvig"
        ]
      },
      "label": "Container info"
    },
    {
      "id": "imwush",
      "name": "heading",
      "parent": "ebgybg",
      "children": [],
      "settings": {
        "_cssGlobalClasses": [
          "alhkaj"
        ],
        "tag": "h1",
        "text": "Lorem ipsum dolor sit amet "
      },
      "label": "Heading"
    },
    {
      "id": "xbrytm",
      "name": "text-basic",
      "parent": "ebgybg",
      "children": [],
      "settings": {
        "text": "Aliqua id fugiat nostrud irure ex duis ea quis id quis ad et. Sunt qui esse pariatur duis deserunt mollit dolore cillum minim tempor enim. Elit aute irure tempor cupidatat incididunt sint deserunt ut.",
        "_cssGlobalClasses": [
          "ccdwgi"
        ]
      },
      "label": "Description"
    },
    {
      "id": "qcuofw",
      "name": "div",
      "parent": "ebgybg",
      "children": [
        "ztyjks",
        "ahbbwx"
      ],
      "settings": {
        "_cssGlobalClasses": [
          "oigyss"
        ]
      },
      "label": "Button container"
    },
    {
      "id": "ztyjks",
      "name": "button",
      "parent": "qcuofw",
      "children": [],
      "settings": {
        "text": "Contact now",
        "_cssGlobalClasses": [
          "bdkjgs"
        ],
        "link": {
          "type": "external",
          "url": "#",
          "ariaLabel": "Go to contact"
        },
        "style": "dark"
      },
      "label": "Button primary"
    },
    {
      "id": "ahbbwx",
      "name": "button",
      "parent": "qcuofw",
      "children": [],
      "settings": {
        "text": "See more",
        "_cssGlobalClasses": [
          "dsmztg"
        ],
        "link": {
          "type": "external",
          "url": "#",
          "ariaLabel": "See more"
        },
        "style": "light",
        "outline": true
      },
      "label": "Button outline"
    },
    {
      "id": "xtsstq",
      "name": "block",
      "parent": "kqpgmm",
      "children": [
        "uefkps",
        "qljrcj"
      ],
      "settings": {
        "_cssGlobalClasses": [
          "npjser"
        ]
      },
      "label": "Container slider"
    },
    {
      "id": "uefkps",
      "name": "slider-nested",
      "parent": "xtsstq",
      "children": [
        "gxbtjz",
        "kxqwte",
        "jjojdz"
      ],
      "settings": {
        "_cssGlobalClasses": [
          "wmbwcs"
        ],
        "type": "fade",
        "rewind": true,
        "pagination": true,
        "height": "90svh",
        "height:tablet_portrait": "auto"
      },
      "label": "Slider",
      "themeStyles": []
    },
    {
      "id": "gxbtjz",
      "name": "div",
      "parent": "uefkps",
      "children": [
        "grqffx"
      ],
      "settings": {
        "_cssGlobalClasses": [
          "vuwoad"
        ]
      },
      "label": "Slide"
    },
    {
      "id": "grqffx",
      "name": "block",
      "parent": "gxbtjz",
      "children": [
        "qehixq",
        "yaqiwt"
      ],
      "settings": {
        "taxonomies": [
          "category",
          "post_tag"
        ],
        "extrasCustomQueryCode": "<style>\nh1.my-heading {\n  color: crimson;\n}\n</style>\n\n<h1 class='my-heading'>Just some custom HTML</h1>",
        "_cssGlobalClasses": [
          "hejttt"
        ],
        "query": {
          "posts_per_page": "3"
        }
      },
      "label": "Card"
    },
    {
      "id": "qehixq",
      "name": "image",
      "parent": "grqffx",
      "children": [],
      "settings": {
        "_cssGlobalClasses": [
          "ikoeyb"
        ],
        "image": {
          "url": "https://acss.brixies.co/wp-content/uploads/2023/10/Img-placeholder-16-9-dark.png",
          "external": true,
          "filename": "Img-placeholder-16-9-dark.png"
        },
        "tag": "figure"
      },
      "themeStyles": []
    },
    {
      "id": "yaqiwt",
      "name": "block",
      "parent": "grqffx",
      "children": [
        "sdbxnq",
        "axjrlt"
      ],
      "settings": {
        "_cssGlobalClasses": [
          "xkgpmv"
        ]
      },
      "label": "Container"
    },
    {
      "id": "sdbxnq",
      "name": "heading",
      "parent": "yaqiwt",
      "children": [],
      "settings": {
        "text": "Lorem ipsum dolor",
        "_cssGlobalClasses": [
          "ftlhle"
        ]
      }
    },
    {
      "id": "axjrlt",
      "name": "text-basic",
      "parent": "yaqiwt",
      "children": [],
      "settings": {
        "text": "Aliqua id fugiat nostrud irure ex duis ea quis id quis ad et.",
        "tag": "p",
        "_cssGlobalClasses": [
          "nvnmpc"
        ]
      },
      "label": "Description"
    },
    {
      "id": "kxqwte",
      "name": "div",
      "parent": "uefkps",
      "children": [
        "eysgnt"
      ],
      "settings": {
        "_cssGlobalClasses": [
          "vuwoad"
        ]
      },
      "label": "Slide"
    },
    {
      "id": "eysgnt",
      "name": "block",
      "parent": "kxqwte",
      "children": [
        "melatq",
        "rwlezl"
      ],
      "settings": {
        "taxonomies": [
          "category",
          "post_tag"
        ],
        "extrasCustomQueryCode": "<style>\nh1.my-heading {\n  color: crimson;\n}\n</style>\n\n<h1 class='my-heading'>Just some custom HTML</h1>",
        "_cssGlobalClasses": [
          "hejttt"
        ],
        "query": {
          "posts_per_page": "3"
        }
      },
      "label": "Card"
    },
    {
      "id": "melatq",
      "name": "image",
      "parent": "eysgnt",
      "children": [],
      "settings": {
        "_cssGlobalClasses": [
          "ikoeyb"
        ],
        "image": {
          "url": "https://acss.brixies.co/wp-content/uploads/2023/10/Img-placeholder-16-9-dark.png",
          "external": true,
          "filename": "Img-placeholder-16-9-dark.png"
        },
        "tag": "figure"
      },
      "themeStyles": []
    },
    {
      "id": "rwlezl",
      "name": "block",
      "parent": "eysgnt",
      "children": [
        "esucqb",
        "aiisss"
      ],
      "settings": {
        "_cssGlobalClasses": [
          "xkgpmv"
        ]
      },
      "label": "Container"
    },
    {
      "id": "esucqb",
      "name": "heading",
      "parent": "rwlezl",
      "children": [],
      "settings": {
        "text": "Lorem ipsum dolor",
        "_cssGlobalClasses": [
          "ftlhle"
        ]
      }
    },
    {
      "id": "aiisss",
      "name": "text-basic",
      "parent": "rwlezl",
      "children": [],
      "settings": {
        "text": "Aliqua id fugiat nostrud irure ex duis ea quis id quis ad et.",
        "tag": "p",
        "_cssGlobalClasses": [
          "nvnmpc"
        ]
      },
      "label": "Description"
    },
    {
      "id": "jjojdz",
      "name": "div",
      "parent": "uefkps",
      "children": [
        "xzqsyi"
      ],
      "settings": {
        "_cssGlobalClasses": [
          "vuwoad"
        ]
      },
      "label": "Slide"
    },
    {
      "id": "xzqsyi",
      "name": "block",
      "parent": "jjojdz",
      "children": [
        "slimpg",
        "jlpqqw"
      ],
      "settings": {
        "taxonomies": [
          "category",
          "post_tag"
        ],
        "extrasCustomQueryCode": "<style>\nh1.my-heading {\n  color: crimson;\n}\n</style>\n\n<h1 class='my-heading'>Just some custom HTML</h1>",
        "_cssGlobalClasses": [
          "hejttt"
        ],
        "query": {
          "posts_per_page": "3"
        }
      },
      "label": "Card"
    },
    {
      "id": "slimpg",
      "name": "image",
      "parent": "xzqsyi",
      "children": [],
      "settings": {
        "_cssGlobalClasses": [
          "ikoeyb"
        ],
        "image": {
          "url": "https://acss.brixies.co/wp-content/uploads/2023/10/Img-placeholder-16-9-dark.png",
          "external": true,
          "filename": "Img-placeholder-16-9-dark.png"
        },
        "tag": "figure"
      },
      "themeStyles": []
    },
    {
      "id": "jlpqqw",
      "name": "block",
      "parent": "xzqsyi",
      "children": [
        "wbdoxi",
        "bnrvpb"
      ],
      "settings": {
        "_cssGlobalClasses": [
          "xkgpmv"
        ]
      },
      "label": "Container"
    },
    {
      "id": "wbdoxi",
      "name": "heading",
      "parent": "jlpqqw",
      "children": [],
      "settings": {
        "text": "Lorem ipsum dolor",
        "_cssGlobalClasses": [
          "ftlhle"
        ]
      }
    },
    {
      "id": "bnrvpb",
      "name": "text-basic",
      "parent": "jlpqqw",
      "children": [],
      "settings": {
        "text": "Aliqua id fugiat nostrud irure ex duis ea quis id quis ad et.",
        "tag": "p",
        "_cssGlobalClasses": [
          "nvnmpc"
        ]
      },
      "label": "Description"
    },
    {
      "id": "qljrcj",
      "name": "block",
      "parent": "xtsstq",
      "children": [
        "xzswre",
        "lwssjr"
      ],
      "settings": {
        "_cssGlobalClasses": [
          "crgjxz"
        ]
      },
      "label": "Pagination container"
    },
    {
      "id": "xzswre",
      "name": "div",
      "parent": "qljrcj",
      "children": [
        "ndspvq"
      ],
      "settings": {
        "_cssGlobalClasses": [
          "yltwhh",
          "pjebii"
        ],
        "tag": "custom",
        "customTag": "button"
      },
      "label": "Arrow left"
    },
    {
      "id": "ndspvq",
      "name": "icon",
      "parent": "xzswre",
      "children": [],
      "settings": {
        "icon": {
          "library": "fontawesomeSolid",
          "icon": "fas fa-arrow-left"
        },
        "_cssGlobalClasses": [
          "wimwzq"
        ]
      },
      "label": "Icon left",
      "themeStyles": []
    },
    {
      "id": "lwssjr",
      "name": "div",
      "parent": "qljrcj",
      "children": [
        "ssqtsj"
      ],
      "settings": {
        "_cssGlobalClasses": [
          "yltwhh",
          "rvqsqz"
        ],
        "tag": "custom",
        "customTag": "button"
      },
      "label": "Arrow Right"
    },
    {
      "id": "ssqtsj",
      "name": "icon",
      "parent": "lwssjr",
      "children": [],
      "settings": {
        "icon": {
          "library": "fontawesomeSolid",
          "icon": "fas fa-arrow-right"
        },
        "_cssGlobalClasses": [
          "wimwzq"
        ]
      },
      "label": "Icon right",
      "themeStyles": []
    },
    {
      "id": "bgtsvc",
      "name": "code",
      "parent": "parhek",
      "children": [],
      "settings": {
        "executeCode": true,
        "signature": "b7d88595fced7b820e69d681c1bc458e",
        "user_id": 2,
        "time": 1720984822,
        "javascriptCode": "document.addEventListener('DOMContentLoaded', (event) => {\n  setTimeout(() => {\n\n    // Get full slider class ID (change if you have changed it manually)\n    const idComplete = document.querySelector(\".hero-38__slider\");\n    // Obtaining the required object ID for the const mySlider\n    const idSlider = idComplete.getAttribute('data-script-id');\n\n    const mySlider = window.bricksData?.splideInstances[idSlider] || false\n\n    // Please replace the button classes to suit your scenario\n    const myPrevBtn = document.querySelector('.hero-38__arrow-left')\n    const myNextBtn = document.querySelector('.hero-38__arrow-right')\n\n    if (mySlider && myPrevBtn && myNextBtn) {\n\n      // Add click event handlers for your custom buttons\n      myPrevBtn.addEventListener('click', function () {\n        mySlider.go('-1') // go() function by SplideJS\n      })\n      myNextBtn.addEventListener('click', function () {\n        mySlider.go('+1') // go() function by SplideJS\n      })\n    }\n  }, 250)\n})"
      },
      "label": "Script slider",
      "themeStyles": []
    }
  ],
  "source": "bricksCopiedElements",
  "sourceUrl": "https://cf.brixies.co",
  "version": "1.12.4",
  "globalClasses": [
    {
      "id": "pspsdj",
      "name": "hero-38",
      "settings": {
        "_background": {
          "color": {
            "raw": "var(--light)",
            "id": "01H7XJZ0KTXZ00FKVG3Y345XCP",
            "name": "light"
          }
        },
        "_position": "relative",
        "_justifyContent": "center",
        "_padding:tablet_portrait": {
          "left": "0",
          "right": "0",
          "bottom": "0"
        },
        "_height:tablet_portrait": "auto",
        "_overflow": "hidden",
        "_heightMin": "90svh"
      }
    },
    {
      "id": "kunmut",
      "name": "hero-38__container",
      "settings": {
        "_columnGap:tablet_portrait": "var(--space-s)",
        "_display": "grid",
        "_gridTemplateColumns": "repeat(2, minmax(0, 1fr))",
        "_gridGap": "var(--space-m)",
        "_gridTemplateColumns:tablet_portrait": "repeat(1, minmax(0, 1fr))",
        "_gridGap:tablet_portrait": "var(--space-l)",
        "_gridTemplateRows": "repeat(1, minmax(0, 1fr))"
      }
    },
    {
      "id": "ntpvig",
      "name": "hero-38__container-info",
      "settings": {
        "_rowGap": "var(--space-m)",
        "_direction:mobile_landscape": "column",
        "_alignItems:mobile_landscape": "stretch",
        "_padding:tablet_portrait": {
          "left": "var(--space-m)",
          "right": "var(--space-m)"
        }
      }
    },
    {
      "id": "alhkaj",
      "name": "hero-38__heading",
      "settings": {
        "_typography": {
          "font-size": "var(--text-2xl)"
        }
      }
    },
    {
      "id": "ccdwgi",
      "name": "hero-38__description",
      "settings": {
        "_widthMax": "540"
      }
    },
    {
      "id": "oigyss",
      "name": "hero-38__btn__container",
      "settings": {
        "_display": "flex",
        "_direction": "row",
        "_columnGap": "var(--space-s)",
        "_rowGap": "var(--space-m)",
        "_width": "100%",
        "_direction:mobile_landscape": "column",
        "_alignItems:mobile_landscape": "stretch",
        "_alignItems": "stretch"
      }
    },
    {
      "id": "bdkjgs",
      "name": "hero-38__btn",
      "settings": {
        "_padding:mobile_landscape": {
          "bottom": "var(--space-s)",
          "top": "var(--space-s)"
        }
      }
    },
    {
      "id": "dsmztg",
      "name": "hero-38__btn--outline",
      "settings": []
    },
    {
      "id": "npjser",
      "name": "hero-38__container-slider",
      "settings": {
        "_width:mobile_landscape": "100%",
        "_position": "absolute",
        "_top": "0",
        "_right": "0",
        "_objectFit": "cover",
        "_width": "calc((100% - var(--space-m)) / 2)",
        "_width:tablet_portrait": "100%",
        "_position:tablet_portrait": "static",
        "_height": "fit-content"
      }
    },
    {
      "id": "wmbwcs",
      "name": "hero-38__slider",
      "settings": {
        "paginationBottom": "var(--space-m)",
        "paginationLeft": "var(--space-m)",
        "paginationColor": {
          "raw": "var(--dark-20)",
          "id": "01H7XJZ4GBR5DD6Q0547QE5P4H.20",
          "name": "dark-20"
        },
        "paginationColorActive": {
          "raw": "var(--dark)",
          "id": "01H7XJZ4GBR5DD6Q0547QE5P4H",
          "name": "dark"
        }
      }
    },
    {
      "id": "vuwoad",
      "name": "card-hero-38__slide",
      "settings": {}
    },
    {
      "id": "hejttt",
      "name": "card-hero-38",
      "settings": {
        "_width": "100%",
        "_direction": "column",
        "_alignItems": "stretch",
        "_justifyContent": "space-between",
        "_height": "100%",
        "_height:tablet_portrait": "auto"
      }
    },
    {
      "id": "ikoeyb",
      "name": "card-hero-38__img",
      "settings": {
        "_width:mobile_landscape": "100%",
        "_objectFit": "cover",
        "_width:tablet_portrait": "100%",
        "_aspectRatio:tablet_portrait": "4 / 3",
        "_position:tablet_portrait": "static",
        "_width": "100%",
        "_objectPosition": "50%",
        "_flexGrow": "1",
        "_heightMin": "1"
      }
    },
    {
      "id": "xkgpmv",
      "name": "card-hero-38__container",
      "settings": {
        "_direction": "column",
        "_flexShrink": "0",
        "_height": "fit-content",
        "_padding": {
          "top": "var(--space-m)",
          "right": "var(--space-m)",
          "bottom": "var(--space-3xl)",
          "left": "var(--space-m)"
        },
        "_rowGap": "var(--space-xs)",
        "_background": {
          "color": {
            "raw": "var(--dark-5)",
            "id": "01H7XJZ4GBR5DD6Q0547QE5P4H.5",
            "name": "dark-5"
          }
        },
        "_padding:tablet_portrait": {
          "bottom": "var(--space-4xl)"
        },
        "_padding:mobile_landscape": {
          "bottom": "var(--space-4xl)"
        },
        "_padding:mobile_portrait": {
          "bottom": "calc(45px + var(--space-4xl))"
        }
      }
    },
    {
      "id": "ftlhle",
      "name": "card-hero-38__heading",
      "settings": {
        "_typography": {
          "font-size": "var(--text-l)"
        }
      }
    },
    {
      "id": "nvnmpc",
      "name": "card-hero-38__description",
      "settings": []
    },
    {
      "id": "crgjxz",
      "name": "hero-38__control-container",
      "settings": {
        "_direction": "row",
        "_justifyContent": "flex-end",
        "_alignItems": "flex-end",
        "_columnGap": "var(--space-xs)",
        "_width": "auto",
        "_flexShrink": "0",
        "_margin:mobile_landscape": {
          "top": "var(--space-s)"
        },
        "_zIndex": "9999",
        "_position": "absolute",
        "_right": "var(--space-m)",
        "_bottom": "var(--space-m)"
      }
    },
    {
      "id": "yltwhh",
      "name": "hero-38__arrow",
      "settings": {
        "_padding": {
          "top": "var(--space-xs)",
          "right": "var(--space-xs)",
          "bottom": "var(--space-xs)",
          "left": "var(--space-xs)"
        },
        "_aspectRatio": "1 / 1",
        "_display": "flex",
        "_justifyContent": "center",
        "_alignItems": "center",
        "_border": {
          "width": {
            "top": "1",
            "right": "1",
            "bottom": "1",
            "left": "1"
          },
          "style": "solid",
          "color": {
            "raw": "var(--dark)",
            "id": "01H7XJZ4GBR5DD6Q0547QE5P4H",
            "name": "dark"
          },
          "radius": {
            "top": "var(--radius-xs)",
            "right": "var(--radius-xs)",
            "bottom": "var(--radius-xs)",
            "left": "var(--radius-xs)"
          }
        },
        "_cursor": "pointer",
        "_background": {
          "color": {
            "raw": "transparent"
          }
        }
      }
    },
    {
      "id": "pjebii",
      "name": "hero-38__arrow-left",
      "settings": []
    },
    {
      "id": "wimwzq",
      "name": "hero-38__arrow-icon",
      "settings": {
        "iconSize": "18",
        "iconColor": {
          "raw": "var(--dark)",
          "id": "01H7XJZ4GBR5DD6Q0547QE5P4H",
          "name": "dark"
        }
      }
    },
    {
      "id": "rvqsqz",
      "name": "hero-38__arrow-right",
      "settings": []
    }
  ],
  "globalElements": []
}